telegram_logger/__init__.py
telegram_logger/__version__.py
telegram_logger/formatters.py
telegram_logger/handlers.py
pyTelegramLogger-1.0.4.dist-info/LICENSE.txt
pyTelegramLogger-1.0.4.dist-info/METADATA
pyTelegramLogger-1.0.4.dist-info/WHEEL
pyTelegramLogger-1.0.4.dist-info/top_level.txt
pyTelegramLogger-1.0.4.dist-info/RECORD
