Metadata-Version: 2.1
Name: pyTelegramLogger
Version: 1.0.4
Summary: This package provides handlers to send logging messages to telegram chats.
Home-page: https://github.com/V-ampire/pyTelegramLogger
Author: V-ampire
Author-email: webjob010@gmail.com
License: MIT
Keywords: telegram,logger,logging,telegram_logger
Classifier: License :: OSI Approved :: MIT License
Classifier: Programming Language :: Python
Classifier: Programming Language :: Python :: 3
Classifier: Programming Language :: Python :: 3.6
Classifier: Programming Language :: Python :: 3.7
Classifier: Programming Language :: Python :: 3.8
Classifier: Programming Language :: Python :: Implementation :: CPython
Requires-Python: >=3.6.0
License-File: LICENSE.txt
Requires-Dist: requests
Provides-Extra: dev
Requires-Dist: factory-boy ; extra == 'dev'
Requires-Dist: pytest ; extra == 'dev'
Requires-Dist: mypy ; extra == 'dev'
Requires-Dist: environs ; extra == 'dev'
